pipchecker/__init__.py
pipchecker/pipcheck.py
pipchecker-0.0.4.dist-info/LICENSE
pipchecker-0.0.4.dist-info/METADATA
pipchecker-0.0.4.dist-info/WHEEL
pipchecker-0.0.4.dist-info/top_level.txt
pipchecker-0.0.4.dist-info/RECORD
