Metadata-Version: 2.1
Name: pipchecker
Version: 0.0.4
Summary: A package for checking pip packages
Home-page: https://github.com/moinonin/pipchecker
Author: Nicolus Rotich
Author-email: nicholas.rotich@gmail.com
License: UNKNOWN
Project-URL: Bug Tracker, https://github.com/pypa/pipchecker/issues
Platform: UNKNOWN
Classifier: Programming Language :: Python :: 3
Classifier: License :: OSI Approved :: MIT License
Classifier: Operating System :: OS Independent
Requires-Python: >=3.6
License-File: LICENSE
